latch_postgres/__init__.py
latch_postgres/postgres.py
latch_postgres/py.typed
latch_postgres/retries.py
latch_postgres-0.2.1.dist-info/METADATA
latch_postgres-0.2.1.dist-info/WHEEL
latch_postgres-0.2.1.dist-info/licenses/LICENSE
latch_postgres-0.2.1.dist-info/RECORD
