Metadata-Version: 2.4
Name: latch-postgres
Version: 0.2.1
Summary: Postges wrapper for latch python backend services
Author-email: maximsmol <max@latch.bio>
License: CC0-1.0
License-File: LICENSE
Requires-Python: >=3.11
Requires-Dist: latch-config<1.0.0,>=0.1.6
Requires-Dist: latch-data-validation<1.0.0,>=0.1.10
Requires-Dist: latch-o11y<2.0.0,>=1.0.0
Requires-Dist: opentelemetry-api<2.0.0,>=1.15.0
Requires-Dist: opentelemetry-sdk<2.0.0,>=1.15.0
Requires-Dist: psycopg[binary,pool]<4.0.0,>=3.2.9
Requires-Dist: typing-extensions<5.0.0,>=4.4.0
